concave/__init__.py
concave/apps/__init__.py
concave/apps/api.py
concave/apps/verify.py
concave/internal/__init__.py
concave/internal/codebase/__init__.py
concave/internal/codebase/manager.py
concave/internal/codebase/search/__init__.py
concave/internal/codebase/search/full_text/__init__.py
concave/internal/codebase/search/full_text/full_text.py
concave/internal/codebase/search/full_text/response.py
concave/internal/codebase/search/symbol/__init__.py
concave/internal/codebase/search/symbol/db.py
concave/internal/codebase/search/symbol/index.py
concave/internal/codebase/search/symbol/proto/__init__.py
concave/internal/codebase/search/symbol/proto/scip.proto
concave/internal/codebase/search/symbol/proto/scip_pb2.py
concave/internal/codebase/search/symbol/proto/scip_pb2.pyi
concave/internal/codebase/search/symbol/scip.py
concave/internal/codebase/search/symbol/searcher.py
concave/internal/codebase/search/vector/__init__.py
concave/internal/codebase/search/vector/vector.py
concave/internal/codebase/tokens/__init__.py
concave/internal/codebase/tokens/tokens.py
concave/internal/datasets/__init__.py
concave/internal/datasets/config.py
concave/internal/datasets/swe_bench/__init__.py
concave/internal/datasets/swe_bench/constants.py
concave/internal/datasets/swe_bench/utils.py
concave/internal/snapshot/__init__.py
concave/internal/snapshot/manager.py
concave/internal/snapshot/snapshot.py
concave/internal/workspace/Index.Dockerfile.j2
concave/internal/workspace/__init__.py
concave/internal/workspace/base.Dockerfile.j2
concave/internal/workspace/config.py
concave/internal/workspace/env.Dockerfile.j2
concave/internal/workspace/file.py
concave/internal/workspace/manager.py
concave/internal/workspace/tools.py
concave/internal/workspace/workspace.Dockerfile.j2
concave/internal/workspace/workspace.py
concave/tools/__init__.py
concave-0.1.5.dist-info/METADATA
concave-0.1.5.dist-info/WHEEL
concave-0.1.5.dist-info/RECORD
